{
  "routes": [
    {
      "method": "GET",
      "path": "/right",
      "handler": "Right.find",
      "config": {
        "policies": []
      }
    },
    {
      "method": "GET",
      "path": "/right/count",
      "handler": "Right.count",
      "config": {
        "policies": []
      }
    },
    {
      "method": "GET",
      "path": "/right/:id",
      "handler": "Right.findOne",
      "config": {
        "policies": []
      }
    },
    {
      "method": "POST",
      "path": "/right",
      "handler": "Right.create",
      "config": {
        "policies": []
      }
    },
    {
      "method": "PUT",
      "path": "/right/:id",
      "handler": "Right.update",
      "config": {
        "policies": []
      }
    },
    {
      "method": "DELETE",
      "path": "/right/:id",
      "handler": "Right.destroy",
      "config": {
        "policies": []
      }
    },
    {
      "method": "POST",
      "path": "/right/:id/relationships/:relation",
      "handler": "Right.createRelation",
      "config": {
        "policies": []
      }
    },
    {
      "method": "PUT",
      "path": "/right/:id/relationships/:relation",
      "handler": "Right.updateRelation",
      "config": {
        "policies": []
      }
    },
    {
      "method": "DELETE",
      "path": "/right/:id/relationships/:relation",
      "handler": "Right.destroyRelation",
      "config": {
        "policies": []
      }
    }
  ]
}
